ex_loghandlers.py
setup.py
version.py
ex_loghandlers.egg-info/PKG-INFO
ex_loghandlers.egg-info/SOURCES.txt
ex_loghandlers.egg-info/dependency_links.txt
ex_loghandlers.egg-info/top_level.txt