Metadata-Version: 1.0
Name: ex-loghandlers
Version: 0.1
Summary: A set of extended logging handlers
Home-page: https://victorlin@bitbucket.org/victorlin/ex_loghandlers
Author: Victor Lin
Author-email: bornstub@gmail.com
License: MIT
Platform: UNKNOWN
